{
  "yawFix": 180,
  "rawPoints": [
    {
      "index": 1,
      "lat": 19.047765000000002,
      "lon": -96.03739287396691,
      "imageUrl": "blob:https://andresmtzc.github.io/fcbb3b36-4b33-4c86-aba0-dc1b30f3abf2"
    },
    {
      "index": 2,
      "lat": 19.04772279111338,
      "lon": -96.03740742120296,
      "imageUrl": "blob:https://andresmtzc.github.io/e39cfbb5-e524-40af-b456-b50e9d1a854d"
    },
    {
      "index": 3,
      "lat": 19.047674010025798,
      "lon": -96.03740815600882,
      "imageUrl": "blob:https://andresmtzc.github.io/b8573225-a760-42ad-a756-233b067f2d8d"
    },
    {
      "index": 4,
      "lat": 19.047625066523683,
      "lon": -96.03740803030075,
      "imageUrl": "blob:https://andresmtzc.github.io/f2351bdc-a7d6-45fc-9834-881ef5fcf603"
    },
    {
      "index": 5,
      "lat": 19.047576448356207,
      "lon": -96.03741481912152,
      "imageUrl": "blob:https://andresmtzc.github.io/e7d44f5a-4e89-4bb7-8edd-83b23e82f1e3"
    },
    {
      "index": 6,
      "lat": 19.047528379081285,
      "lon": -96.03742563496269,
      "imageUrl": "blob:https://andresmtzc.github.io/e43ecbec-6289-4a22-a5cd-58e8272f2dee"
    },
    {
      "index": 7,
      "lat": 19.047480178290165,
      "lon": -96.03743566682661,
      "imageUrl": "blob:https://andresmtzc.github.io/27a73d41-3f84-4715-a736-da501c303e80"
    },
    {
      "index": 8,
      "lat": 19.047431206274943,
      "lon": -96.03744027500971,
      "imageUrl": "blob:https://andresmtzc.github.io/1674d457-e656-4bf9-917f-918c4e0a804f"
    },
    {
      "index": 9,
      "lat": 19.047382458273283,
      "lon": -96.03743459681618,
      "imageUrl": "blob:https://andresmtzc.github.io/3bd8e381-c839-43ce-b421-efd5bb302648"
    },
    {
      "index": 10,
      "lat": 19.047333770065865,
      "lon": -96.03742780562568,
      "imageUrl": "blob:https://andresmtzc.github.io/bc054783-9099-4b1d-b275-3e6c5586c1cd"
    },
    {
      "index": 11,
      "lat": 19.047285664211984,
      "lon": -96.03741716625392,
      "imageUrl": "blob:https://andresmtzc.github.io/4b53ba94-53c2-4a4e-b3ae-86148890da03"
    },
    {
      "index": 12,
      "lat": 19.04723708007196,
      "lon": -96.03740926722679,
      "imageUrl": "blob:https://andresmtzc.github.io/aa138b90-337a-48b0-97ef-f78033b2fed4"
    },
    {
      "index": 13,
      "lat": 19.04718809072894,
      "lon": -96.0374049821737,
      "imageUrl": "blob:https://andresmtzc.github.io/39a5ba9e-a89e-4d24-92b4-cb4887547d0f"
    },
    {
      "index": 14,
      "lat": 19.047139239229207,
      "lon": -96.03739942123977,
      "imageUrl": "blob:https://andresmtzc.github.io/ccc4f9f7-580c-4db1-b733-35f7188c92ad"
    },
    {
      "index": 15,
      "lat": 19.04709037533443,
      "lon": -96.03739369339164,
      "imageUrl": "blob:https://andresmtzc.github.io/b82df7a3-07f0-475a-be76-4388ccaa8b85"
    },
    {
      "index": 16,
      "lat": 19.047041482237123,
      "lon": -96.03738852399628,
      "imageUrl": "blob:https://andresmtzc.github.io/612efda2-6d9f-4082-b2b4-5760fae52670"
    },
    {
      "index": 17,
      "lat": 19.046992425588076,
      "lon": -96.03739025508156,
      "imageUrl": "blob:https://andresmtzc.github.io/a1937b98-0298-4557-a9bf-2cd11e76519f"
    },
    {
      "index": 18,
      "lat": 19.046943859683388,
      "lon": -96.03739786225742,
      "imageUrl": "blob:https://andresmtzc.github.io/86833c26-571e-491f-b221-51881a350ccc"
    },
    {
      "index": 19,
      "lat": 19.046898398339394,
      "lon": -96.0374170359522,
      "imageUrl": "blob:https://andresmtzc.github.io/d430ea87-3083-4908-8bd9-0efc75b95888"
    },
    {
      "index": 20,
      "lat": 19.046858828911873,
      "lon": -96.03744763579708,
      "imageUrl": "blob:https://andresmtzc.github.io/1979f694-2e8e-4941-8c85-a40cbd8adf11"
    },
    {
      "index": 21,
      "lat": 19.04682618548973,
      "lon": -96.03748649408787,
      "imageUrl": "blob:https://andresmtzc.github.io/a5d77b21-44a7-468a-8d98-76edcf159085"
    },
    {
      "index": 22,
      "lat": 19.046800970907597,
      "lon": -96.03753070449808,
      "imageUrl": "blob:https://andresmtzc.github.io/0fbc51a4-c0c0-44f5-8d60-97b365d4986f"
    },
    {
      "index": 23,
      "lat": 19.046782176541083,
      "lon": -96.03757872781424,
      "imageUrl": "blob:https://andresmtzc.github.io/a57579d9-f2c3-46e5-b9d8-6b0c9f4f25ec"
    },
    {
      "index": 24,
      "lat": 19.046767783291894,
      "lon": -96.0376283847509,
      "imageUrl": "blob:https://andresmtzc.github.io/69cb660c-9c02-4aeb-bfea-ed6a3780059b"
    },
    {
      "index": 25,
      "lat": 19.04675254685411,
      "lon": -96.03767761284159,
      "imageUrl": "blob:https://andresmtzc.github.io/fb2a7dd4-b6ad-4028-a0c6-6867c9ab972d"
    },
    {
      "index": 26,
      "lat": 19.0467446597002,
      "lon": -96.03772894363067,
      "imageUrl": "blob:https://andresmtzc.github.io/d8cacfc6-1660-4b5a-a56f-1d0b5055808c"
    },
    {
      "index": 27,
      "lat": 19.046745101990613,
      "lon": -96.03778070018541,
      "imageUrl": "blob:https://andresmtzc.github.io/c37c037b-e9e9-4709-91e2-b887b8c293e2"
    },
    {
      "index": 28,
      "lat": 19.046734366183138,
      "lon": -96.03783132918251,
      "imageUrl": "blob:https://andresmtzc.github.io/0da770a5-6494-4548-9938-f0d2049255ce"
    },
    {
      "index": 29,
      "lat": 19.046724236826368,
      "lon": -96.03788222812986,
      "imageUrl": "blob:https://andresmtzc.github.io/4f435d24-a024-4707-9f37-6e7c14ef5597"
    },
    {
      "index": 30,
      "lat": 19.04670837099924,
      "lon": -96.03793133634011,
      "imageUrl": "blob:https://andresmtzc.github.io/c2e5c1f5-86b6-4e25-9da7-270ddaae9d4a"
    },
    {
      "index": 31,
      "lat": 19.04669630956407,
      "lon": -96.03798166386999,
      "imageUrl": "blob:https://andresmtzc.github.io/4821438c-6cd6-45a6-b171-bf4f12c4e4de"
    },
    {
      "index": 32,
      "lat": 19.046681710169057,
      "lon": -96.03803126973841,
      "imageUrl": "blob:https://andresmtzc.github.io/922811ad-9373-44b1-901e-ee989124dbce"
    },
    {
      "index": 33,
      "lat": 19.046667255454746,
      "lon": -96.03808097192281,
      "imageUrl": "blob:https://andresmtzc.github.io/d94886ce-74da-4b8b-8590-1096e391877b"
    },
    {
      "index": 34,
      "lat": 19.046648964578146,
      "lon": -96.03812921794433,
      "imageUrl": "blob:https://andresmtzc.github.io/8aa0f87d-6b11-4041-957a-bcf70abd1c7e"
    },
    {
      "index": 35,
      "lat": 19.046633817596504,
      "lon": -96.03817869185428,
      "imageUrl": "blob:https://andresmtzc.github.io/5c28d9b8-b12e-463a-b0e1-67b5465fad97"
    },
    {
      "index": 36,
      "lat": 19.046617089287054,
      "lon": -96.03822757721419,
      "imageUrl": "blob:https://andresmtzc.github.io/4b6ab2b4-f047-4d0b-828d-504c644358ce"
    },
    {
      "index": 37,
      "lat": 19.046595709391703,
      "lon": -96.03827442736602,
      "imageUrl": "blob:https://andresmtzc.github.io/7f2c35f9-1a34-4a68-a6a3-9f0c7d65b6f2"
    },
    {
      "index": 38,
      "lat": 19.04657857614574,
      "lon": -96.03832296307728,
      "imageUrl": "blob:https://andresmtzc.github.io/9e1339c1-0a9f-4b9c-8a98-11290a66965e"
    },
    {
      "index": 39,
      "lat": 19.04656099632579,
      "lon": -96.03837154234805,
      "imageUrl": "blob:https://andresmtzc.github.io/62d4ca8a-a195-43f1-b4c9-bc9d6e9353df"
    },
    {
      "index": 40,
      "lat": 19.04654998393173,
      "lon": -96.03842222110386,
      "imageUrl": "blob:https://andresmtzc.github.io/d4571480-d443-4c84-8acf-a125aef74341"
    },
    {
      "index": 41,
      "lat": 19.04653752627112,
      "lon": -96.03847250122016,
      "imageUrl": "blob:https://andresmtzc.github.io/ce4d2928-4823-400e-9c5d-4eb8d63c601c"
    },
    {
      "index": 42,
      "lat": 19.046526952638228,
      "lon": -96.03852319367485,
      "imageUrl": "blob:https://andresmtzc.github.io/c8c29e34-0a4b-4d87-bf26-980658081f70"
    },
    {
      "index": 43,
      "lat": 19.046519429385786,
      "lon": -96.03857439925014,
      "imageUrl": "blob:https://andresmtzc.github.io/f3d7aa2d-058f-49a8-9c0b-2ec940bf26f0"
    },
    {
      "index": 44,
      "lat": 19.046508010517254,
      "lon": -96.0386249382162,
      "imageUrl": "blob:https://andresmtzc.github.io/a0cf5a28-72a5-4b25-86e1-1c94227f8211"
    },
    {
      "index": 45,
      "lat": 19.046498053581548,
      "lon": -96.03867582744157,
      "imageUrl": "blob:https://andresmtzc.github.io/7011ff75-ea9d-4962-9c3c-9729cdcb8b88"
    },
    {
      "index": 46,
      "lat": 19.046486820899514,
      "lon": -96.03872635396922,
      "imageUrl": "blob:https://andresmtzc.github.io/04741ead-e723-4fe4-8b6f-8eaaf0b417cc"
    },
    {
      "index": 47,
      "lat": 19.04647064445629,
      "lon": -96.03877540754085,
      "imageUrl": "blob:https://andresmtzc.github.io/f988d213-4edb-4956-9da5-0e3b74d852af"
    },
    {
      "index": 48,
      "lat": 19.046453818124593,
      "lon": -96.03882425509536,
      "imageUrl": "blob:https://andresmtzc.github.io/9c817ad7-8bb2-48e1-b236-2e369e76e751"
    },
    {
      "index": 49,
      "lat": 19.04643694264507,
      "lon": -96.03887311147744,
      "imageUrl": "blob:https://andresmtzc.github.io/d75d2e7f-7fa9-4e58-986f-596d75bd19cf"
    },
    {
      "index": 50,
      "lat": 19.046420731489484,
      "lon": -96.03892222331413,
      "imageUrl": "blob:https://andresmtzc.github.io/1604dd18-f39c-49f6-9700-1782969b5f89"
    },
    {
      "index": 51,
      "lat": 19.046405528427606,
      "lon": -96.03897168659492,
      "imageUrl": "blob:https://andresmtzc.github.io/2cda7b87-c44d-473d-b0dc-580b19e87fc8"
    },
    {
      "index": 52,
      "lat": 19.046387391108404,
      "lon": -96.03902005643155,
      "imageUrl": "blob:https://andresmtzc.github.io/031e18a9-819d-4e29-87dd-13183f7adea5"
    },
    {
      "index": 53,
      "lat": 19.04637464072082,
      "lon": -96.039070286799,
      "imageUrl": "blob:https://andresmtzc.github.io/97e4b37b-30bb-4cd2-b40f-1dc12895b941"
    },
    {
      "index": 54,
      "lat": 19.04636018424289,
      "lon": -96.03911998698119,
      "imageUrl": "blob:https://andresmtzc.github.io/982caad2-f087-4472-ae4e-3f48f4b991cd"
    },
    {
      "index": 55,
      "lat": 19.04634389653397,
      "lon": -96.03916905319312,
      "imageUrl": "blob:https://andresmtzc.github.io/68187e10-ee23-4c52-86cc-82612f0b3d0d"
    },
    {
      "index": 56,
      "lat": 19.04632499837587,
      "lon": -96.03921703755499,
      "imageUrl": "blob:https://andresmtzc.github.io/20b3ba92-e2a0-4c39-b2c4-a1056844a40f"
    },
    {
      "index": 57,
      "lat": 19.046309881473846,
      "lon": -96.03926648617728,
      "imageUrl": "blob:https://andresmtzc.github.io/324a2063-f22c-45dc-85f6-1d12c4ada27c"
    },
    {
      "index": 58,
      "lat": 19.04629885485705,
      "lon": -96.03931715234177,
      "imageUrl": "blob:https://andresmtzc.github.io/ff98a5fb-6bdf-4c14-bacd-4c426c73371f"
    },
    {
      "index": 59,
      "lat": 19.04628684323106,
      "lon": -96.03936758489348,
      "imageUrl": "blob:https://andresmtzc.github.io/ff94c12f-66e3-44f5-83d7-768cff5895b3"
    },
    {
      "index": 60,
      "lat": 19.046270557052857,
      "lon": -96.0394166697826,
      "imageUrl": "blob:https://andresmtzc.github.io/5b111356-df99-4f84-9e4a-c2c10a0bd85d"
    },
    {
      "index": 61,
      "lat": 19.046272748351974,
      "lon": -96.03946611483639,
      "imageUrl": "blob:https://andresmtzc.github.io/7692cafa-8688-4614-aa57-3ae83b40c2a8"
    },
    {
      "index": 62,
      "lat": 19.04630967208162,
      "lon": -96.03949930047762,
      "imageUrl": "blob:https://andresmtzc.github.io/5d375d4a-cc50-4931-9343-96689f569ac0"
    },
    {
      "index": 63,
      "lat": 19.046357645568996,
      "lon": -96.03949860692417,
      "imageUrl": "blob:https://andresmtzc.github.io/8aa3bf09-8f54-4b62-a6e8-ed38b68088af"
    },
    {
      "index": 64,
      "lat": 19.046400574942812,
      "lon": -96.03947357133035,
      "imageUrl": "blob:https://andresmtzc.github.io/17d5ca88-0cbe-43eb-8d97-891a32846662"
    },
    {
      "index": 65,
      "lat": 19.046441572781287,
      "lon": -96.03944493211965,
      "imageUrl": "blob:https://andresmtzc.github.io/4a9d7406-7701-46f4-aa0c-8edbffc7556b"
    },
    {
      "index": 66,
      "lat": 19.04647961092391,
      "lon": -96.03941195295977,
      "imageUrl": "blob:https://andresmtzc.github.io/6767a76d-f202-45cd-a089-67c0f0cbcc20"
    },
    {
      "index": 67,
      "lat": 19.046520053534113,
      "lon": -96.039382450414,
      "imageUrl": "blob:https://andresmtzc.github.io/7d38071e-cddf-4ec6-aecc-d685f01cb82e"
    },
    {
      "index": 68,
      "lat": 19.046557814295618,
      "lon": -96.03934937336147,
      "imageUrl": "blob:https://andresmtzc.github.io/7f41fb3b-2193-4df6-bea6-4cee8d10b16e"
    },
    {
      "index": 69,
      "lat": 19.046579282317307,
      "lon": -96.03930355644223,
      "imageUrl": "blob:https://andresmtzc.github.io/c5ddc647-77c8-4cb5-87b4-3b3573d401fc"
    },
    {
      "index": 70,
      "lat": 19.04658895048532,
      "lon": -96.03925267013598,
      "imageUrl": "blob:https://andresmtzc.github.io/9b009303-97df-4195-8d6f-d3b8e543adec"
    },
    {
      "index": 71,
      "lat": 19.04658694584566,
      "lon": -96.03920075350692,
      "imageUrl": "blob:https://andresmtzc.github.io/8f4079ea-47f3-4a42-9a30-bed03b85ec35"
    },
    {
      "index": 72,
      "lat": 19.04658091792884,
      "lon": -96.03914914416002,
      "imageUrl": "blob:https://andresmtzc.github.io/5df306a2-02be-4318-a2de-e4b8e71c5196"
    },
    {
      "index": 73,
      "lat": 19.046578304718363,
      "lon": -96.03909729800753,
      "imageUrl": "blob:https://andresmtzc.github.io/be0d6819-72f4-4c5a-bd35-bd990b86e897"
    },
    {
      "index": 74,
      "lat": 19.046582236358304,
      "lon": -96.03904544248137,
      "imageUrl": "blob:https://andresmtzc.github.io/d8e42c90-8956-46a6-b2f8-8140497fa51e"
    },
    {
      "index": 75,
      "lat": 19.046582854660336,
      "lon": -96.03899342388227,
      "imageUrl": "blob:https://andresmtzc.github.io/1123c33b-082a-4e9b-8f8e-493d371ef7b2"
    },
    {
      "index": 76,
      "lat": 19.04658349614367,
      "lon": -96.03894136159653,
      "imageUrl": "blob:https://andresmtzc.github.io/d561a552-5c90-479c-b552-844004c103f2"
    },
    {
      "index": 77,
      "lat": 19.04657983931764,
      "lon": -96.0388894813387,
      "imageUrl": "blob:https://andresmtzc.github.io/75b3a8d9-ef5d-423f-9c7a-838dbbd555bb"
    },
    {
      "index": 78,
      "lat": 19.04657622622512,
      "lon": -96.0388376276994,
      "imageUrl": "blob:https://andresmtzc.github.io/67a56cbf-fddc-4f88-8416-4e7da47eb395"
    },
    {
      "index": 79,
      "lat": 19.046574876430995,
      "lon": -96.0387856680916,
      "imageUrl": "blob:https://andresmtzc.github.io/29f5ddae-1916-41f6-b068-d6f458911385"
    },
    {
      "index": 80,
      "lat": 19.04657389949072,
      "lon": -96.03873366534954,
      "imageUrl": "blob:https://andresmtzc.github.io/89c3aaec-ba09-4e9a-8f2f-5499ce0dbd1c"
    },
    {
      "index": 81,
      "lat": 19.046572494662826,
      "lon": -96.03868166738638,
      "imageUrl": "blob:https://andresmtzc.github.io/9c1a5efb-f306-434e-a087-cd58a9138bcc"
    },
    {
      "index": 82,
      "lat": 19.046567530419036,
      "lon": -96.03862993034971,
      "imageUrl": "blob:https://andresmtzc.github.io/61088d55-b64a-4f72-b6fa-2966d76adf4a"
    },
    {
      "index": 83,
      "lat": 19.046563302922156,
      "lon": -96.03857817948736,
      "imageUrl": "blob:https://andresmtzc.github.io/1f045463-f59f-4baa-bdd3-576bcb9a61e0"
    },
    {
      "index": 84,
      "lat": 19.046566962865853,
      "lon": -96.03852630668007,
      "imageUrl": "blob:https://andresmtzc.github.io/fccc0b7e-dbaa-4020-afbc-f6f5e1aa9a81"
    },
    {
      "index": 85,
      "lat": 19.04657174628867,
      "lon": -96.03847454760712,
      "imageUrl": "blob:https://andresmtzc.github.io/95412f07-4d67-45c1-9360-0ae0da5ea22e"
    },
    {
      "index": 86,
      "lat": 19.04657449807973,
      "lon": -96.03842282810629,
      "imageUrl": "blob:https://andresmtzc.github.io/1bf5691d-c84b-49d3-a9f4-02915823c3ec"
    },
    {
      "index": 87,
      "lat": 19.04657500544496,
      "lon": -96.03837107905203,
      "imageUrl": "blob:https://andresmtzc.github.io/6636c333-240f-4e57-890b-60019e4fe542"
    },
    {
      "index": 88,
      "lat": 19.046608207730394,
      "lon": -96.03833651748002,
      "imageUrl": "blob:https://andresmtzc.github.io/59d02d92-357f-4c59-89a4-3939fb010b5b"
    },
    {
      "index": 89,
      "lat": 19.046655400065145,
      "lon": -96.03832355734372,
      "imageUrl": "blob:https://andresmtzc.github.io/3752199f-e196-4b91-b88a-3431a801652a"
    },
    {
      "index": 90,
      "lat": 19.046704508387183,
      "lon": -96.03832113754504,
      "imageUrl": "blob:https://andresmtzc.github.io/c83e7976-4fca-466b-bcee-4c4b39b6e4db"
    },
    {
      "index": 91,
      "lat": 19.046753217967076,
      "lon": -96.03832761200967,
      "imageUrl": "blob:https://andresmtzc.github.io/26898356-5f9c-40de-a2b2-6dc4e2488664"
    },
    {
      "index": 92,
      "lat": 19.04680231943792,
      "lon": -96.03832951358727,
      "imageUrl": "blob:https://andresmtzc.github.io/91d25a13-ea29-4501-825f-4a8af02f4fa5"
    },
    {
      "index": 93,
      "lat": 19.046851356904305,
      "lon": -96.03833322748818,
      "imageUrl": "blob:https://andresmtzc.github.io/4fe713bd-d74d-4db4-9762-cd40b6b692d6"
    },
    {
      "index": 94,
      "lat": 19.046900308171487,
      "lon": -96.03833702713935,
      "imageUrl": "blob:https://andresmtzc.github.io/3bea3b85-ead2-4908-a49b-90e9d1990632"
    }
  ],
  "controlPoints": [
    {
      "lon": -96.0373719402617,
      "lat": 19.0476832657928
    },
    {
      "lon": -96.03741069144199,
      "lat": 19.047342963272797
    },
    {
      "lon": -96.03747691394221,
      "lat": 19.046789393180035
    },
    {
      "lon": -96.03786533802631,
      "lat": 19.046631429820167
    },
    {
      "lon": -96.03822342663656,
      "lat": 19.04651246453612
    },
    {
      "lon": -96.0385031469356,
      "lat": 19.04643493474677
    },
    {
      "lon": -96.03926025182888,
      "lat": 19.04626132520427
    },
    {
      "lon": -96.03949085251094,
      "lat": 19.04627289917869
    },
    {
      "lon": -96.0394010610952,
      "lat": 19.046450366696874
    },
    {
      "lon": -96.03928882182497,
      "lat": 19.046535242399514
    },
    {
      "lon": -96.038950063301,
      "lat": 19.046521739449474
    },
    {
      "lon": -96.03867864833917,
      "lat": 19.046508236499236
    },
    {
      "lon": -96.0383326680436,
      "lat": 19.046600038178127
    },
    {
      "lon": -96.03828747473473,
      "lat": 19.04687194295984
    }
  ],
  "redMarkers": [
    {
      "sequentialIndex": 0,
      "originalImageIndex": 1,
      "lat": 19.0476832657928,
      "lon": -96.0373719402617,
      "distanceAlongRoute": 0,
      "isLocked": true
    },
    {
      "sequentialIndex": 1,
      "originalImageIndex": 2,
      "lat": 19.047644280656154,
      "lon": -96.03737633521797,
      "distanceAlongRoute": 0.00435949889060956,
      "isLocked": false
    },
    {
      "sequentialIndex": 2,
      "originalImageIndex": 3,
      "lat": 19.047605293027953,
      "lon": -96.03738070540376,
      "distanceAlongRoute": 0.008718997786312023,
      "isLocked": false
    },
    {
      "sequentialIndex": 3,
      "originalImageIndex": 4,
      "lat": 19.04756630615483,
      "lon": -96.03738508311905,
      "distanceAlongRoute": 0.013078496666168232,
      "isLocked": false
    },
    {
      "sequentialIndex": 4,
      "originalImageIndex": 5,
      "lat": 19.04752732118055,
      "lon": -96.03738947971529,
      "distanceAlongRoute": 0.017437995557571306,
      "isLocked": false
    },
    {
      "sequentialIndex": 5,
      "originalImageIndex": 6,
      "lat": 19.04748833876246,
      "lon": -96.03739390160176,
      "distanceAlongRoute": 0.02179749444786753,
      "isLocked": false
    },
    {
      "sequentialIndex": 6,
      "originalImageIndex": 7,
      "lat": 19.04744935940105,
      "lon": -96.03739835353996,
      "distanceAlongRoute": 0.02615699332567476,
      "isLocked": false
    },
    {
      "sequentialIndex": 7,
      "originalImageIndex": 8,
      "lat": 19.04741038351658,
      "lon": -96.0374028394137,
      "distanceAlongRoute": 0.030516492209660535,
      "isLocked": false
    },
    {
      "sequentialIndex": 8,
      "originalImageIndex": 9,
      "lat": 19.047371411502443,
      "lon": -96.03740736276272,
      "distanceAlongRoute": 0.03487599113057225,
      "isLocked": true
    },
    {
      "sequentialIndex": 9,
      "originalImageIndex": 10,
      "lat": 19.047321455951465,
      "lon": -96.0374128090736,
      "distanceAlongRoute": 0.040460529676961114,
      "isLocked": false
    },
    {
      "sequentialIndex": 10,
      "originalImageIndex": 11,
      "lat": 19.04727132132723,
      "lon": -96.03741588591578,
      "distanceAlongRoute": 0.04604506822334998,
      "isLocked": false
    },
    {
      "sequentialIndex": 11,
      "originalImageIndex": 12,
      "lat": 19.047221122589843,
      "lon": -96.0374175097808,
      "distanceAlongRoute": 0.051629606769738844,
      "isLocked": false
    },
    {
      "sequentialIndex": 12,
      "originalImageIndex": 13,
      "lat": 19.047170909781816,
      "lon": -96.03741857236396,
      "distanceAlongRoute": 0.05721414531612771,
      "isLocked": false
    },
    {
      "sequentialIndex": 13,
      "originalImageIndex": 14,
      "lat": 19.047120697665562,
      "lon": -96.03741966983247,
      "distanceAlongRoute": 0.06279868386251658,
      "isLocked": false
    },
    {
      "sequentialIndex": 14,
      "originalImageIndex": 15,
      "lat": 19.047070498481364,
      "lon": -96.03742128468464,
      "distanceAlongRoute": 0.06838322240890543,
      "isLocked": false
    },
    {
      "sequentialIndex": 15,
      "originalImageIndex": 16,
      "lat": 19.047020337062722,
      "lon": -96.03742388248277,
      "distanceAlongRoute": 0.07396776095529431,
      "isLocked": false
    },
    {
      "sequentialIndex": 16,
      "originalImageIndex": 17,
      "lat": 19.046970268224918,
      "lon": -96.03742799915173,
      "distanceAlongRoute": 0.07955229950168316,
      "isLocked": false
    },
    {
      "sequentialIndex": 17,
      "originalImageIndex": 18,
      "lat": 19.046920425759176,
      "lon": -96.03743446928743,
      "distanceAlongRoute": 0.08513683804807204,
      "isLocked": false
    },
    {
      "sequentialIndex": 18,
      "originalImageIndex": 19,
      "lat": 19.046871107486705,
      "lon": -96.03744440784754,
      "distanceAlongRoute": 0.09072137659446089,
      "isLocked": false
    },
    {
      "sequentialIndex": 19,
      "originalImageIndex": 20,
      "lat": 19.04682310039365,
      "lon": -96.037459842179,
      "distanceAlongRoute": 0.09630591514084977,
      "isLocked": false
    },
    {
      "sequentialIndex": 20,
      "originalImageIndex": 21,
      "lat": 19.04677868752144,
      "lon": -96.03748434473253,
      "distanceAlongRoute": 0.10189045368723862,
      "isLocked": false
    },
    {
      "sequentialIndex": 21,
      "originalImageIndex": 22,
      "lat": 19.04674205767972,
      "lon": -96.03752045526342,
      "distanceAlongRoute": 0.1074749922336275,
      "isLocked": false
    },
    {
      "sequentialIndex": 22,
      "originalImageIndex": 23,
      "lat": 19.046714610176384,
      "lon": -96.0375648175191,
      "distanceAlongRoute": 0.11305953078001635,
      "isLocked": false
    },
    {
      "sequentialIndex": 23,
      "originalImageIndex": 24,
      "lat": 19.046694855115877,
      "lon": -96.03761361237798,
      "distanceAlongRoute": 0.11864406932640523,
      "isLocked": false
    },
    {
      "sequentialIndex": 24,
      "originalImageIndex": 25,
      "lat": 19.04668032214185,
      "lon": -96.03766445412992,
      "distanceAlongRoute": 0.12422860787279408,
      "isLocked": false
    },
    {
      "sequentialIndex": 25,
      "originalImageIndex": 26,
      "lat": 19.04666865290325,
      "lon": -96.03771612818646,
      "distanceAlongRoute": 0.12981314641918296,
      "isLocked": false
    },
    {
      "sequentialIndex": 26,
      "originalImageIndex": 27,
      "lat": 19.046657794262018,
      "lon": -96.03776800305724,
      "distanceAlongRoute": 0.1353976849655718,
      "isLocked": false
    },
    {
      "sequentialIndex": 27,
      "originalImageIndex": 28,
      "lat": 19.04664564679926,
      "lon": -96.03781955066114,
      "distanceAlongRoute": 0.14098222351196069,
      "isLocked": false
    },
    {
      "sequentialIndex": 28,
      "originalImageIndex": 29,
      "lat": 19.046629739424514,
      "lon": -96.03786991827904,
      "distanceAlongRoute": 0.14656676205834954,
      "isLocked": true
    },
    {
      "sequentialIndex": 29,
      "originalImageIndex": 30,
      "lat": 19.046612416356904,
      "lon": -96.03791768267308,
      "distanceAlongRoute": 0.15194404729643687,
      "isLocked": false
    },
    {
      "sequentialIndex": 30,
      "originalImageIndex": 31,
      "lat": 19.04659561964617,
      "lon": -96.03796565712038,
      "distanceAlongRoute": 0.15732133253452418,
      "isLocked": false
    },
    {
      "sequentialIndex": 31,
      "originalImageIndex": 32,
      "lat": 19.046579284895447,
      "lon": -96.03801380983695,
      "distanceAlongRoute": 0.16269861777261152,
      "isLocked": false
    },
    {
      "sequentialIndex": 32,
      "originalImageIndex": 33,
      "lat": 19.046563348820246,
      "lon": -96.03806211187937,
      "distanceAlongRoute": 0.16807590301069883,
      "isLocked": false
    },
    {
      "sequentialIndex": 33,
      "originalImageIndex": 34,
      "lat": 19.046547751240375,
      "lon": -96.03811053746396,
      "distanceAlongRoute": 0.17345318824878617,
      "isLocked": false
    },
    {
      "sequentialIndex": 34,
      "originalImageIndex": 35,
      "lat": 19.04653243374253,
      "lon": -96.0381590630361,
      "distanceAlongRoute": 0.17883047348687348,
      "isLocked": false
    },
    {
      "sequentialIndex": 35,
      "originalImageIndex": 36,
      "lat": 19.04651732851441,
      "lon": -96.03820766304872,
      "distanceAlongRoute": 0.1842077587249608,
      "isLocked": false
    },
    {
      "sequentialIndex": 36,
      "originalImageIndex": 37,
      "lat": 19.04650226079479,
      "lon": -96.03825627606594,
      "distanceAlongRoute": 0.18958504396304812,
      "isLocked": false
    },
    {
      "sequentialIndex": 37,
      "originalImageIndex": 38,
      "lat": 19.046487091300886,
      "lon": -96.03830485362492,
      "distanceAlongRoute": 0.19496232920113546,
      "isLocked": false
    },
    {
      "sequentialIndex": 38,
      "originalImageIndex": 39,
      "lat": 19.04647278265557,
      "lon": -96.03835372066892,
      "distanceAlongRoute": 0.20033961443922277,
      "isLocked": false
    },
    {
      "sequentialIndex": 39,
      "originalImageIndex": 40,
      "lat": 19.046459723121778,
      "lon": -96.03840297868047,
      "distanceAlongRoute": 0.2057168996773101,
      "isLocked": false
    },
    {
      "sequentialIndex": 40,
      "originalImageIndex": 41,
      "lat": 19.046447323037413,
      "lon": -96.03845242781192,
      "distanceAlongRoute": 0.21109418491539741,
      "isLocked": false
    },
    {
      "sequentialIndex": 41,
      "originalImageIndex": 42,
      "lat": 19.046435222863042,
      "lon": -96.03850196017888,
      "distanceAlongRoute": 0.21647147015348472,
      "isLocked": false
    },
    {
      "sequentialIndex": 42,
      "originalImageIndex": 43,
      "lat": 19.04642316669988,
      "lon": -96.03855150459053,
      "distanceAlongRoute": 0.22184875539157206,
      "isLocked": false
    },
    {
      "sequentialIndex": 43,
      "originalImageIndex": 44,
      "lat": 19.04641106855944,
      "lon": -96.03860103755135,
      "distanceAlongRoute": 0.2272260406296594,
      "isLocked": false
    },
    {
      "sequentialIndex": 44,
      "originalImageIndex": 45,
      "lat": 19.04639897555132,
      "lon": -96.03865057191102,
      "distanceAlongRoute": 0.23260332586774674,
      "isLocked": false
    },
    {
      "sequentialIndex": 45,
      "originalImageIndex": 46,
      "lat": 19.04638691433812,
      "lon": -96.03870011494023,
      "distanceAlongRoute": 0.23798061110583404,
      "isLocked": false
    },
    {
      "sequentialIndex": 46,
      "originalImageIndex": 47,
      "lat": 19.046374902782883,
      "lon": -96.03874967146311,
      "distanceAlongRoute": 0.24335789634392135,
      "isLocked": false
    },
    {
      "sequentialIndex": 47,
      "originalImageIndex": 48,
      "lat": 19.046362955152055,
      "lon": -96.03879924527274,
      "distanceAlongRoute": 0.2487351815820087,
      "isLocked": false
    },
    {
      "sequentialIndex": 48,
      "originalImageIndex": 49,
      "lat": 19.046351093000865,
      "lon": -96.0388488420458,
      "distanceAlongRoute": 0.25411246682009603,
      "isLocked": false
    },
    {
      "sequentialIndex": 49,
      "originalImageIndex": 50,
      "lat": 19.046339331683644,
      "lon": -96.03889846567311,
      "distanceAlongRoute": 0.25948975205818336,
      "isLocked": false
    },
    {
      "sequentialIndex": 50,
      "originalImageIndex": 51,
      "lat": 19.046327688551354,
      "lon": -96.03894812047145,
      "distanceAlongRoute": 0.26486703729627065,
      "isLocked": false
    },
    {
      "sequentialIndex": 51,
      "originalImageIndex": 52,
      "lat": 19.046316197238504,
      "lon": -96.0389978148321,
      "distanceAlongRoute": 0.270244322534358,
      "isLocked": false
    },
    {
      "sequentialIndex": 52,
      "originalImageIndex": 53,
      "lat": 19.046304901012483,
      "lon": -96.03904755919349,
      "distanceAlongRoute": 0.27562160777244527,
      "isLocked": false
    },
    {
      "sequentialIndex": 53,
      "originalImageIndex": 54,
      "lat": 19.04629384845177,
      "lon": -96.03909736470864,
      "distanceAlongRoute": 0.2809988930105326,
      "isLocked": false
    },
    {
      "sequentialIndex": 54,
      "originalImageIndex": 55,
      "lat": 19.046283130577972,
      "lon": -96.0391472519078,
      "distanceAlongRoute": 0.28637617824861994,
      "isLocked": false
    },
    {
      "sequentialIndex": 55,
      "originalImageIndex": 56,
      "lat": 19.046272904139233,
      "lon": -96.03919725417659,
      "distanceAlongRoute": 0.2917534634867073,
      "isLocked": false
    },
    {
      "sequentialIndex": 56,
      "originalImageIndex": 57,
      "lat": 19.046263514291223,
      "lon": -96.03924743867856,
      "distanceAlongRoute": 0.2971307487247946,
      "isLocked": false
    },
    {
      "sequentialIndex": 57,
      "originalImageIndex": 58,
      "lat": 19.046255445692214,
      "lon": -96.03929787970209,
      "distanceAlongRoute": 0.30250803396288195,
      "isLocked": false
    },
    {
      "sequentialIndex": 58,
      "originalImageIndex": 59,
      "lat": 19.04624876899299,
      "lon": -96.0393485460515,
      "distanceAlongRoute": 0.3078853192009693,
      "isLocked": false
    },
    {
      "sequentialIndex": 59,
      "originalImageIndex": 60,
      "lat": 19.04624482556315,
      "lon": -96.03939951978984,
      "distanceAlongRoute": 0.31326260443905657,
      "isLocked": false
    },
    {
      "sequentialIndex": 60,
      "originalImageIndex": 61,
      "lat": 19.04624817440778,
      "lon": -96.03945041136168,
      "distanceAlongRoute": 0.3186398896771439,
      "isLocked": false
    },
    {
      "sequentialIndex": 61,
      "originalImageIndex": 62,
      "lat": 19.046274365988328,
      "lon": -96.0394917238418,
      "distanceAlongRoute": 0.3240171749152312,
      "isLocked": false
    },
    {
      "sequentialIndex": 62,
      "originalImageIndex": 63,
      "lat": 19.046320978844292,
      "lon": -96.03948642610126,
      "distanceAlongRoute": 0.3293944601533185,
      "isLocked": false
    },
    {
      "sequentialIndex": 63,
      "originalImageIndex": 64,
      "lat": 19.046363975045363,
      "lon": -96.03946311237398,
      "distanceAlongRoute": 0.33477174539140586,
      "isLocked": false
    },
    {
      "sequentialIndex": 64,
      "originalImageIndex": 65,
      "lat": 19.04640465786297,
      "lon": -96.0394354697688,
      "distanceAlongRoute": 0.3401490306294932,
      "isLocked": false
    },
    {
      "sequentialIndex": 65,
      "originalImageIndex": 66,
      "lat": 19.04644410640199,
      "lon": -96.03940588170147,
      "distanceAlongRoute": 0.3455263158675805,
      "isLocked": false
    },
    {
      "sequentialIndex": 66,
      "originalImageIndex": 67,
      "lat": 19.046484177971998,
      "lon": -96.03937726430561,
      "distanceAlongRoute": 0.3509036011056679,
      "isLocked": false
    },
    {
      "sequentialIndex": 67,
      "originalImageIndex": 68,
      "lat": 19.04651866569773,
      "lon": -96.03934208009755,
      "distanceAlongRoute": 0.35628088634375515,
      "isLocked": false
    },
    {
      "sequentialIndex": 68,
      "originalImageIndex": 69,
      "lat": 19.04653435871369,
      "lon": -96.0392939803617,
      "distanceAlongRoute": 0.3616581715818425,
      "isLocked": false
    },
    {
      "sequentialIndex": 69,
      "originalImageIndex": 70,
      "lat": 19.04653870914359,
      "lon": -96.03924308859747,
      "distanceAlongRoute": 0.3670354568199298,
      "isLocked": false
    },
    {
      "sequentialIndex": 70,
      "originalImageIndex": 71,
      "lat": 19.046538088567026,
      "lon": -96.03919194097607,
      "distanceAlongRoute": 0.3724127420580171,
      "isLocked": false
    },
    {
      "sequentialIndex": 71,
      "originalImageIndex": 72,
      "lat": 19.046535404078536,
      "lon": -96.03914086188121,
      "distanceAlongRoute": 0.37779002729610445,
      "isLocked": false
    },
    {
      "sequentialIndex": 72,
      "originalImageIndex": 73,
      "lat": 19.04653172716876,
      "lon": -96.03908985052378,
      "distanceAlongRoute": 0.3831673125341918,
      "isLocked": false
    },
    {
      "sequentialIndex": 73,
      "originalImageIndex": 74,
      "lat": 19.046527700715675,
      "lon": -96.03903886835175,
      "distanceAlongRoute": 0.3885445977722791,
      "isLocked": false
    },
    {
      "sequentialIndex": 74,
      "originalImageIndex": 75,
      "lat": 19.04652391162961,
      "lon": -96.03898786616357,
      "distanceAlongRoute": 0.39392188301036646,
      "isLocked": false
    },
    {
      "sequentialIndex": 75,
      "originalImageIndex": 76,
      "lat": 19.04652103320581,
      "lon": -96.03893679825306,
      "distanceAlongRoute": 0.3992991682484537,
      "isLocked": false
    },
    {
      "sequentialIndex": 76,
      "originalImageIndex": 77,
      "lat": 19.046516625118276,
      "lon": -96.03888585734322,
      "distanceAlongRoute": 0.404676453486541,
      "isLocked": false
    },
    {
      "sequentialIndex": 77,
      "originalImageIndex": 78,
      "lat": 19.04651067960209,
      "lon": -96.03883508597065,
      "distanceAlongRoute": 0.41005373872462836,
      "isLocked": false
    },
    {
      "sequentialIndex": 78,
      "originalImageIndex": 79,
      "lat": 19.046505688200625,
      "lon": -96.03878420503365,
      "distanceAlongRoute": 0.4154310239627157,
      "isLocked": false
    },
    {
      "sequentialIndex": 79,
      "originalImageIndex": 80,
      "lat": 19.04650427268965,
      "lon": -96.0387330875199,
      "distanceAlongRoute": 0.42080830920080303,
      "isLocked": false
    },
    {
      "sequentialIndex": 80,
      "originalImageIndex": 81,
      "lat": 19.046507833632937,
      "lon": -96.03868209231749,
      "distanceAlongRoute": 0.42618559443889037,
      "isLocked": false
    },
    {
      "sequentialIndex": 81,
      "originalImageIndex": 82,
      "lat": 19.046514142612427,
      "lon": -96.03863136987151,
      "distanceAlongRoute": 0.4315628796769777,
      "isLocked": false
    },
    {
      "sequentialIndex": 82,
      "originalImageIndex": 83,
      "lat": 19.046520931357094,
      "lon": -96.03858071742395,
      "distanceAlongRoute": 0.43694016491506504,
      "isLocked": false
    },
    {
      "sequentialIndex": 83,
      "originalImageIndex": 84,
      "lat": 19.046528896600545,
      "lon": -96.0385302585848,
      "distanceAlongRoute": 0.44231745015315227,
      "isLocked": false
    },
    {
      "sequentialIndex": 84,
      "originalImageIndex": 85,
      "lat": 19.046538761980358,
      "lon": -96.03848017979536,
      "distanceAlongRoute": 0.4476947353912397,
      "isLocked": false
    },
    {
      "sequentialIndex": 85,
      "originalImageIndex": 86,
      "lat": 19.04655150373011,
      "lon": -96.0384308409361,
      "distanceAlongRoute": 0.45307202062932694,
      "isLocked": false
    },
    {
      "sequentialIndex": 86,
      "originalImageIndex": 87,
      "lat": 19.046568792480432,
      "lon": -96.03838310111497,
      "distanceAlongRoute": 0.4584493058674143,
      "isLocked": false
    },
    {
      "sequentialIndex": 87,
      "originalImageIndex": 88,
      "lat": 19.04659405389544,
      "lon": -96.03833964069867,
      "distanceAlongRoute": 0.4638265911055016,
      "isLocked": false
    },
    {
      "sequentialIndex": 88,
      "originalImageIndex": 89,
      "lat": 19.046632701959677,
      "lon": -96.03830969174628,
      "distanceAlongRoute": 0.46920387634358895,
      "isLocked": false
    },
    {
      "sequentialIndex": 89,
      "originalImageIndex": 90,
      "lat": 19.046678958583552,
      "lon": -96.03829520594331,
      "distanceAlongRoute": 0.4745811615816763,
      "isLocked": false
    },
    {
      "sequentialIndex": 90,
      "originalImageIndex": 91,
      "lat": 19.046726958555265,
      "lon": -96.0382892547221,
      "distanceAlongRoute": 0.47995844681976363,
      "isLocked": false
    },
    {
      "sequentialIndex": 91,
      "originalImageIndex": 92,
      "lat": 19.046775290803243,
      "lon": -96.03828786668565,
      "distanceAlongRoute": 0.48533573205785085,
      "isLocked": false
    },
    {
      "sequentialIndex": 92,
      "originalImageIndex": 93,
      "lat": 19.04682364336904,
      "lon": -96.03828864811739,
      "distanceAlongRoute": 0.4907130172959383,
      "isLocked": false
    },
    {
      "sequentialIndex": 93,
      "originalImageIndex": 94,
      "lat": 19.04687194295984,
      "lon": -96.03828747473473,
      "distanceAlongRoute": 0.49609030253402553,
      "isLocked": true
    }
  ],
  "marriages": [
    [
      "marsella1:29",
      "marsella2:1"
    ],
    [
      "marsella1:87",
      "marsella1:39"
    ],
    [
      "marsella2:29",
      "marsella1:94"
    ],
    [
      "marsella3:1",
      "marsella2:53"
    ],
    [
      "marsella3:17",
      "marsella2:21"
    ],
    [
      "marsella2:77",
      "marsella3:27"
    ],
    [
      "marsella3:53",
      "marsella1:1"
    ],
    [
      "marsella3:63",
      "marsella3:160"
    ]
  ]
}